connorav/__init__.py
connorav/correl_rv.py
connorav/distribution.py
connorav-0.2.1.dist-info/licenses/LICENSE
connorav-0.2.1.dist-info/METADATA
connorav-0.2.1.dist-info/WHEEL
connorav-0.2.1.dist-info/top_level.txt
connorav-0.2.1.dist-info/RECORD
