Metadata-Version: 2.4
Name: connorav
Version: 0.2.1
Summary: Fast Generation of Correlated Non-Normal Random Variates
Author-email: Chris Bates <1314008+chrsbats@users.noreply.github.com>
License-Expression: MIT
Project-URL: Homepage, https://github.com/chrsbats/connorav
Project-URL: Issues, https://github.com/chrsbats/connorav/issues
Classifier: Programming Language :: Python :: 3
Classifier: Programming Language :: Python :: 3 :: Only
Classifier: Programming Language :: Python :: 3.9
Classifier: Programming Language :: Python :: 3.10
Classifier: Programming Language :: Python :: 3.11
Classifier: Programming Language :: Python :: 3.12
Classifier: Programming Language :: Python :: 3.13
Classifier: Operating System :: OS Independent
Classifier: Topic :: Scientific/Engineering
Classifier: Topic :: Software Development :: Libraries
Requires-Python: >=3.9
License-File: LICENSE
Requires-Dist: numpy<2.0,>=1.22; python_version < "3.10"
Requires-Dist: numpy>=1.26; python_version >= "3.10"
Requires-Dist: scipy<1.12,>=1.10; python_version < "3.10"
Requires-Dist: scipy>=1.13; python_version >= "3.10"
Provides-Extra: dev
Requires-Dist: pytest>=7; extra == "dev"
Requires-Dist: pytest-cov>=4; extra == "dev"
Requires-Dist: pytest-randomly>=3.12; extra == "dev"
Requires-Dist: pytest-repeat>=0.9; extra == "dev"
Dynamic: license-file
